eve_panel/__init__.py
eve_panel/auth/__init__.py
eve_panel/auth/base.py
eve_panel/auth/basic_auth.py
eve_panel/auth/bearer.py
eve_panel/auth/oauth2.py
eve_panel/auth/panel_oauth.py
eve_panel/eve_client.py
eve_panel/eve_model.py
eve_panel/exceptions.py
eve_panel/field.py
eve_panel/io.py
eve_panel/item.py
eve_panel/menu.py
eve_panel/page.py
eve_panel/resource.py
eve_panel/schema.py
eve_panel/session.py
eve_panel/settings.py
eve_panel/types.py
eve_panel/utils.py
eve_panel/web_client.py
eve_panel/widgets.py
eve_panel-0.3.28.dist-info/LICENSE
eve_panel-0.3.28.dist-info/WHEEL
eve_panel-0.3.28.dist-info/METADATA
eve_panel-0.3.28.dist-info/RECORD
