Metadata-Version: 2.1
Name: eve-panel
Version: 0.3.28
Summary: Top-level package for Eve-Panel.
Home-page: https://jmosbacher.github.io/eve-panel
License: MIT
Author: Yossi Mosbacher
Author-email: joe.mosbacher@gmail.com
Requires-Python: >=3.8,<3.11
Classifier: Development Status :: 2 - Pre-Alpha
Classifier: Intended Audience :: Developers
Classifier: License :: OSI Approved :: MIT License
Classifier: Natural Language :: English
Classifier: Programming Language :: Python :: 3
Classifier: Programming Language :: Python :: 3.10
Classifier: Programming Language :: Python :: 3.6
Classifier: Programming Language :: Python :: 3.7
Classifier: Programming Language :: Python :: 3.8
Classifier: Programming Language :: Python :: 3.9
Provides-Extra: dask
Provides-Extra: full
Provides-Extra: plotting
Requires-Dist: dask
Requires-Dist: eve (>=1.1.3,<2.0.0)
Requires-Dist: httpx (>=0.19,<0.20)
Requires-Dist: hvplot; extra == "plotting" or extra == "full"
Requires-Dist: numpy
Requires-Dist: panel (>=0.13.0,<0.14.0)
Project-URL: Documentation, https://eve-panel.readthedocs.io
